contextual_langdetect/__init__.py
contextual_langdetect/detection.py
contextual_langdetect/exceptions.py
contextual_langdetect/py.typed
contextual_langdetect-0.2.0.dist-info/METADATA
contextual_langdetect-0.2.0.dist-info/WHEEL
contextual_langdetect-0.2.0.dist-info/licenses/LICENSE
contextual_langdetect-0.2.0.dist-info/RECORD
