Metadata-Version: 2.4
Name: contextual-langdetect
Version: 0.2.0
Summary: Context-aware language detection with improved accuracy for multilingual documents
Project-URL: Homepage, https://github.com/osteele/contextual-langdetect
Project-URL: Documentation, https://osteele.github.io/contextual-langdetect/
Project-URL: Issues, https://github.com/osteele/contextual-langdetect/issues
Project-URL: Source, https://github.com/osteele/contextual-langdetect
Author-email: Oliver Steele <steele@osteele.com>
License: MIT
License-File: LICENSE
Keywords: context-aware,i18n,language-detection,linguistics,multilingual,natural-language-processing,nlp
Classifier: Development Status :: 3 - Alpha
Classifier: Intended Audience :: Developers
Classifier: License :: OSI Approved :: MIT License
Classifier: Programming Language :: Python :: 3.11
Classifier: Topic :: Text Processing
Classifier: Topic :: Text Processing :: Linguistic
Requires-Python: >=3.9
Requires-Dist: fast-langdetect>=0.3.2
